ai_commands/__init__.py
ai_commands/ai_commands.py
ai_commands-1.0.0.dist-info/LICENSE
ai_commands-1.0.0.dist-info/METADATA
ai_commands-1.0.0.dist-info/WHEEL
ai_commands-1.0.0.dist-info/top_level.txt
ai_commands-1.0.0.dist-info/RECORD
