Metadata-Version: 2.1
Name: ai-commands
Version: 1.0.0
Summary: A Python package for simple but complex computer functions.
Author: MKM12345
Author-email: MKM12345 <arekhon.shadow@gmail.com>
Project-URL: Homepage, https://github.com/MKM12345/ai-commands
Project-URL: Bug Tracker, https://github.com/MKM12345/ai-commands/issues
Keywords: python,AI,sentiment analysis,natural language processing
Classifier: Programming Language :: Python :: 3
Classifier: License :: OSI Approved :: MIT License
Classifier: Operating System :: OS Independent
Requires-Python: >=3.7
License-File: LICENSE
Requires-Dist: nltk
Requires-Dist: textblob
Requires-Dist: transformers
Requires-Dist: torch
Requires-Dist: networkx
Requires-Dist: langdetect
Requires-Dist: Pillow
Requires-Dist: spacy
